LICENCE
README.md
setup.py
pycmd/__init__.py
python_cmd_w.egg-info/PKG-INFO
python_cmd_w.egg-info/SOURCES.txt
python_cmd_w.egg-info/dependency_links.txt
python_cmd_w.egg-info/requires.txt
python_cmd_w.egg-info/top_level.txt